[
    {
        "timestamp": "2025-03-26T00:00:01.313124",
        "arduino_error": "Error fetching Arduino data: HTTPConnectionPool(host='10.205.104.247', port=80): Max retries exceeded with url: / (Caused by NewConnectionError('<urllib3.connection.HTTPConnection object at 0x7fffa9e9a7d0>: Failed to establish a new connection: [Errno 113] No route to host'))",
        "co2_sensor_data": 0,
        "outdoor_temperature": 6022,
        "supply_air_flow_pressure": 0,
        "supply_air_flow": 14,
        "ahu_filter_pressure_level": 1127,
        "fan_levels": 10000,
        "reheat_regulation_level": 0,
        "cooling_regulation_level": 0,
        "duct_pressure": 0,
        "voc_level": 0,
        "rhx_operation_level": 8415,
        "rhx_efficiency": 0,
        "rhx_defrost_pressure_level": 0,
        "heat_exchanger_regulator_lvl": 0,
        "room_temp_set_point": 16,
        "min_temperature_set_point": 0,
        "max_temperature_set_point": 0
    },
    {
        "timestamp": "2025-03-26T00:10:01.271242",
        "arduino_error": "Error fetching Arduino data: HTTPConnectionPool(host='10.205.104.247', port=80): Max retries exceeded with url: / (Caused by NewConnectionError('<urllib3.connection.HTTPConnection object at 0x7ffefb40a6d0>: Failed to establish a new connection: [Errno 113] No route to host'))",
        "co2_sensor_data": 0,
        "outdoor_temperature": 6022,
        "supply_air_flow_pressure": 0,
        "supply_air_flow": 13,
        "ahu_filter_pressure_level": 2456,
        "fan_levels": 10000,
        "reheat_regulation_level": 0,
        "cooling_regulation_level": 0,
        "duct_pressure": 0,
        "voc_level": 0,
        "rhx_operation_level": 8403,
        "rhx_efficiency": 0,
        "rhx_defrost_pressure_level": 0,
        "heat_exchanger_regulator_lvl": 0,
        "room_temp_set_point": 16,
        "min_temperature_set_point": 0,
        "max_temperature_set_point": 0
    },
    {
        "timestamp": "2025-03-26T00:20:02.034025",
        "arduino_error": "Error fetching Arduino data: HTTPConnectionPool(host='10.205.104.247', port=80): Max retries exceeded with url: / (Caused by NewConnectionError('<urllib3.connection.HTTPConnection object at 0x7fff03bfa6d0>: Failed to establish a new connection: [Errno 113] No route to host'))",
        "co2_sensor_data": 0,
        "outdoor_temperature": 6022,
        "supply_air_flow_pressure": 0,
        "supply_air_flow": 14,
        "ahu_filter_pressure_level": 3265,
        "fan_levels": 6015,
        "reheat_regulation_level": 0,
        "cooling_regulation_level": 0,
        "duct_pressure": 0,
        "voc_level": 0,
        "rhx_operation_level": 8403,
        "rhx_efficiency": 0,
        "rhx_defrost_pressure_level": 0,
        "heat_exchanger_regulator_lvl": 0,
        "room_temp_set_point": 16,
        "min_temperature_set_point": 0,
        "max_temperature_set_point": 0
    },
    {
        "timestamp": "2025-03-26T00:30:01.781677",
        "arduino_error": "Error fetching Arduino data: HTTPConnectionPool(host='10.205.104.247', port=80): Max retries exceeded with url: / (Caused by NewConnectionError('<urllib3.connection.HTTPConnection object at 0x7fff9db0a6d0>: Failed to establish a new connection: [Errno 113] No route to host'))",
        "co2_sensor_data": 0,
        "outdoor_temperature": 6022,
        "supply_air_flow_pressure": 0,
        "supply_air_flow": 14,
        "ahu_filter_pressure_level": 2448,
        "fan_levels": 10000,
        "reheat_regulation_level": 0,
        "cooling_regulation_level": 0,
        "duct_pressure": 0,
        "voc_level": 0,
        "rhx_operation_level": 8404,
        "rhx_efficiency": 0,
        "rhx_defrost_pressure_level": 0,
        "heat_exchanger_regulator_lvl": 0,
        "room_temp_set_point": 16,
        "min_temperature_set_point": 0,
        "max_temperature_set_point": 0
    },
    {
        "timestamp": "2025-03-26T00:40:01.569515",
        "arduino_error": "Error fetching Arduino data: HTTPConnectionPool(host='10.205.104.247', port=80): Max retries exceeded with url: / (Caused by NewConnectionError('<urllib3.connection.HTTPConnection object at 0x7fff59d2a7d0>: Failed to establish a new connection: [Errno 113] No route to host'))",
        "co2_sensor_data": 0,
        "outdoor_temperature": 6022,
        "supply_air_flow_pressure": 0,
        "supply_air_flow": 13,
        "ahu_filter_pressure_level": 1188,
        "fan_levels": 10000,
        "reheat_regulation_level": 0,
        "cooling_regulation_level": 0,
        "duct_pressure": 0,
        "voc_level": 0,
        "rhx_operation_level": 8402,
        "rhx_efficiency": 0,
        "rhx_defrost_pressure_level": 0,
        "heat_exchanger_regulator_lvl": 0,
        "room_temp_set_point": 16,
        "min_temperature_set_point": 0,
        "max_temperature_set_point": 0
    },
    {
        "timestamp": "2025-03-26T00:50:01.578419",
        "arduino_error": "Error fetching Arduino data: HTTPConnectionPool(host='10.205.104.247', port=80): Max retries exceeded with url: / (Caused by NewConnectionError('<urllib3.connection.HTTPConnection object at 0x7fff92c2a6d0>: Failed to establish a new connection: [Errno 113] No route to host'))",
        "co2_sensor_data": 0,
        "outdoor_temperature": 6022,
        "supply_air_flow_pressure": 0,
        "supply_air_flow": 14,
        "ahu_filter_pressure_level": 2591,
        "fan_levels": 7955,
        "reheat_regulation_level": 0,
        "cooling_regulation_level": 0,
        "duct_pressure": 0,
        "voc_level": 0,
        "rhx_operation_level": 8400,
        "rhx_efficiency": 0,
        "rhx_defrost_pressure_level": 0,
        "heat_exchanger_regulator_lvl": 0,
        "room_temp_set_point": 16,
        "min_temperature_set_point": 0,
        "max_temperature_set_point": 0
    },
    {
        "timestamp": "2025-03-26T01:00:01.316753",
        "arduino_error": "Error fetching Arduino data: HTTPConnectionPool(host='10.205.104.247', port=80): Max retries exceeded with url: / (Caused by NewConnectionError('<urllib3.connection.HTTPConnection object at 0x7fff205ca7d0>: Failed to establish a new connection: [Errno 113] No route to host'))",
        "co2_sensor_data": 0,
        "outdoor_temperature": 6022,
        "supply_air_flow_pressure": 0,
        "supply_air_flow": 14,
        "ahu_filter_pressure_level": 3223,
        "fan_levels": 10000,
        "reheat_regulation_level": 0,
        "cooling_regulation_level": 0,
        "duct_pressure": 0,
        "voc_level": 0,
        "rhx_operation_level": 8400,
        "rhx_efficiency": 0,
        "rhx_defrost_pressure_level": 0,
        "heat_exchanger_regulator_lvl": 0,
        "room_temp_set_point": 16,
        "min_temperature_set_point": 0,
        "max_temperature_set_point": 0
    },
    {
        "timestamp": "2025-03-26T01:10:02.048061",
        "arduino_error": "Error fetching Arduino data: HTTPConnectionPool(host='10.205.104.247', port=80): Max retries exceeded with url: / (Caused by NewConnectionError('<urllib3.connection.HTTPConnection object at 0x7fff6fcca6d0>: Failed to establish a new connection: [Errno 113] No route to host'))",
        "co2_sensor_data": 0,
        "outdoor_temperature": 6022,
        "supply_air_flow_pressure": 0,
        "supply_air_flow": 14,
        "ahu_filter_pressure_level": 1606,
        "fan_levels": 10000,
        "reheat_regulation_level": 0,
        "cooling_regulation_level": 0,
        "duct_pressure": 0,
        "voc_level": 0,
        "rhx_operation_level": 8405,
        "rhx_efficiency": 0,
        "rhx_defrost_pressure_level": 0,
        "heat_exchanger_regulator_lvl": 0,
        "room_temp_set_point": 16,
        "min_temperature_set_point": 0,
        "max_temperature_set_point": 0
    },
    {
        "timestamp": "2025-03-26T01:20:01.508636",
        "arduino_error": "Error fetching Arduino data: HTTPConnectionPool(host='10.205.104.247', port=80): Max retries exceeded with url: / (Caused by NewConnectionError('<urllib3.connection.HTTPConnection object at 0x7fff5bd1a6d0>: Failed to establish a new connection: [Errno 113] No route to host'))",
        "co2_sensor_data": 0,
        "outdoor_temperature": 6022,
        "supply_air_flow_pressure": 0,
        "supply_air_flow": 13,
        "ahu_filter_pressure_level": 1676,
        "fan_levels": 10000,
        "reheat_regulation_level": 0,
        "cooling_regulation_level": 0,
        "duct_pressure": 0,
        "voc_level": 0,
        "rhx_operation_level": 8403,
        "rhx_efficiency": 0,
        "rhx_defrost_pressure_level": 0,
        "heat_exchanger_regulator_lvl": 0,
        "room_temp_set_point": 16,
        "min_temperature_set_point": 0,
        "max_temperature_set_point": 0
    },
    {
        "timestamp": "2025-03-26T01:30:01.428243",
        "arduino_error": "Error fetching Arduino data: HTTPConnectionPool(host='10.205.104.247', port=80): Max retries exceeded with url: / (Caused by NewConnectionError('<urllib3.connection.HTTPConnection object at 0x7ffec6aaa6d0>: Failed to establish a new connection: [Errno 113] No route to host'))",
        "co2_sensor_data": 0,
        "outdoor_temperature": 6022,
        "supply_air_flow_pressure": 0,
        "supply_air_flow": 14,
        "ahu_filter_pressure_level": 3205,
        "fan_levels": 7017,
        "reheat_regulation_level": 0,
        "cooling_regulation_level": 0,
        "duct_pressure": 0,
        "voc_level": 0,
        "rhx_operation_level": 8403,
        "rhx_efficiency": 0,
        "rhx_defrost_pressure_level": 0,
        "heat_exchanger_regulator_lvl": 0,
        "room_temp_set_point": 16,
        "min_temperature_set_point": 0,
        "max_temperature_set_point": 0
    },
    {
        "timestamp": "2025-03-26T01:40:01.757792",
        "arduino_error": "Error fetching Arduino data: HTTPConnectionPool(host='10.205.104.247', port=80): Max retries exceeded with url: / (Caused by NewConnectionError('<urllib3.connection.HTTPConnection object at 0x7fff44f8a7d0>: Failed to establish a new connection: [Errno 113] No route to host'))",
        "co2_sensor_data": 0,
        "outdoor_temperature": 6022,
        "supply_air_flow_pressure": 0,
        "supply_air_flow": 12,
        "ahu_filter_pressure_level": 3110,
        "fan_levels": 10000,
        "reheat_regulation_level": 0,
        "cooling_regulation_level": 0,
        "duct_pressure": 0,
        "voc_level": 0,
        "rhx_operation_level": 8399,
        "rhx_efficiency": 0,
        "rhx_defrost_pressure_level": 0,
        "heat_exchanger_regulator_lvl": 0,
        "room_temp_set_point": 16,
        "min_temperature_set_point": 0,
        "max_temperature_set_point": 0
    },
    {
        "timestamp": "2025-03-26T01:50:01.401573",
        "arduino_error": "Error fetching Arduino data: HTTPConnectionPool(host='10.205.104.247', port=80): Max retries exceeded with url: / (Caused by NewConnectionError('<urllib3.connection.HTTPConnection object at 0x7ffec29ea6d0>: Failed to establish a new connection: [Errno 113] No route to host'))",
        "co2_sensor_data": 0,
        "outdoor_temperature": 6022,
        "supply_air_flow_pressure": 0,
        "supply_air_flow": 13,
        "ahu_filter_pressure_level": 2245,
        "fan_levels": 10000,
        "reheat_regulation_level": 0,
        "cooling_regulation_level": 0,
        "duct_pressure": 0,
        "voc_level": 0,
        "rhx_operation_level": 8401,
        "rhx_efficiency": 0,
        "rhx_defrost_pressure_level": 0,
        "heat_exchanger_regulator_lvl": 0,
        "room_temp_set_point": 16,
        "min_temperature_set_point": 0,
        "max_temperature_set_point": 0
    },
    {
        "timestamp": "2025-03-26T02:00:01.863419",
        "arduino_error": "Error fetching Arduino data: HTTPConnectionPool(host='10.205.104.247', port=80): Max retries exceeded with url: / (Caused by NewConnectionError('<urllib3.connection.HTTPConnection object at 0x7ffeffd0a6d0>: Failed to establish a new connection: [Errno 113] No route to host'))",
        "co2_sensor_data": 0,
        "outdoor_temperature": 6022,
        "supply_air_flow_pressure": 0,
        "supply_air_flow": 13,
        "ahu_filter_pressure_level": 1617,
        "fan_levels": 10000,
        "reheat_regulation_level": 0,
        "cooling_regulation_level": 0,
        "duct_pressure": 0,
        "voc_level": 0,
        "rhx_operation_level": 8400,
        "rhx_efficiency": 0,
        "rhx_defrost_pressure_level": 0,
        "heat_exchanger_regulator_lvl": 0,
        "room_temp_set_point": 16,
        "min_temperature_set_point": 0,
        "max_temperature_set_point": 0
    },
    {
        "timestamp": "2025-03-26T02:10:01.889388",
        "arduino_error": "Error fetching Arduino data: HTTPConnectionPool(host='10.205.104.247', port=80): Max retries exceeded with url: / (Caused by NewConnectionError('<urllib3.connection.HTTPConnection object at 0x7ffef325a7d0>: Failed to establish a new connection: [Errno 113] No route to host'))",
        "co2_sensor_data": 0,
        "outdoor_temperature": 6022,
        "supply_air_flow_pressure": 0,
        "supply_air_flow": 13,
        "ahu_filter_pressure_level": 2299,
        "fan_levels": 10000,
        "reheat_regulation_level": 0,
        "cooling_regulation_level": 0,
        "duct_pressure": 0,
        "voc_level": 0,
        "rhx_operation_level": 8403,
        "rhx_efficiency": 0,
        "rhx_defrost_pressure_level": 0,
        "heat_exchanger_regulator_lvl": 0,
        "room_temp_set_point": 16,
        "min_temperature_set_point": 0,
        "max_temperature_set_point": 0
    },
    {
        "timestamp": "2025-03-26T02:20:01.571238",
        "arduino_error": "Error fetching Arduino data: HTTPConnectionPool(host='10.205.104.247', port=80): Max retries exceeded with url: / (Caused by NewConnectionError('<urllib3.connection.HTTPConnection object at 0x7ffebfe1a6d0>: Failed to establish a new connection: [Errno 113] No route to host'))",
        "co2_sensor_data": 0,
        "outdoor_temperature": 6022,
        "supply_air_flow_pressure": 0,
        "supply_air_flow": 14,
        "ahu_filter_pressure_level": 1491,
        "fan_levels": 10000,
        "reheat_regulation_level": 0,
        "cooling_regulation_level": 0,
        "duct_pressure": 0,
        "voc_level": 0,
        "rhx_operation_level": 8404,
        "rhx_efficiency": 0,
        "rhx_defrost_pressure_level": 0,
        "heat_exchanger_regulator_lvl": 0,
        "room_temp_set_point": 16,
        "min_temperature_set_point": 0,
        "max_temperature_set_point": 0
    },
    {
        "timestamp": "2025-03-26T02:30:01.635557",
        "arduino_error": "Error fetching Arduino data: HTTPConnectionPool(host='10.205.104.247', port=80): Max retries exceeded with url: / (Caused by NewConnectionError('<urllib3.connection.HTTPConnection object at 0x7ffee90da7d0>: Failed to establish a new connection: [Errno 113] No route to host'))",
        "co2_sensor_data": 0,
        "outdoor_temperature": 6022,
        "supply_air_flow_pressure": 0,
        "supply_air_flow": 13,
        "ahu_filter_pressure_level": 3211,
        "fan_levels": 6565,
        "reheat_regulation_level": 0,
        "cooling_regulation_level": 0,
        "duct_pressure": 0,
        "voc_level": 0,
        "rhx_operation_level": 8400,
        "rhx_efficiency": 0,
        "rhx_defrost_pressure_level": 0,
        "heat_exchanger_regulator_lvl": 0,
        "room_temp_set_point": 16,
        "min_temperature_set_point": 0,
        "max_temperature_set_point": 0
    },
    {
        "timestamp": "2025-03-26T02:40:01.266048",
        "arduino_error": "Error fetching Arduino data: HTTPConnectionPool(host='10.205.104.247', port=80): Max retries exceeded with url: / (Caused by NewConnectionError('<urllib3.connection.HTTPConnection object at 0x7ffed3aba6d0>: Failed to establish a new connection: [Errno 113] No route to host'))",
        "co2_sensor_data": 0,
        "outdoor_temperature": 6022,
        "supply_air_flow_pressure": 0,
        "supply_air_flow": 13,
        "ahu_filter_pressure_level": 2840,
        "fan_levels": 10000,
        "reheat_regulation_level": 0,
        "cooling_regulation_level": 0,
        "duct_pressure": 0,
        "voc_level": 0,
        "rhx_operation_level": 8401,
        "rhx_efficiency": 0,
        "rhx_defrost_pressure_level": 0,
        "heat_exchanger_regulator_lvl": 0,
        "room_temp_set_point": 16,
        "min_temperature_set_point": 0,
        "max_temperature_set_point": 0
    },
    {
        "timestamp": "2025-03-26T02:50:01.432138",
        "arduino_error": "Error fetching Arduino data: HTTPConnectionPool(host='10.205.104.247', port=80): Max retries exceeded with url: / (Caused by NewConnectionError('<urllib3.connection.HTTPConnection object at 0x7fff9228a7d0>: Failed to establish a new connection: [Errno 113] No route to host'))",
        "co2_sensor_data": 0,
        "outdoor_temperature": 6022,
        "supply_air_flow_pressure": 0,
        "supply_air_flow": 13,
        "ahu_filter_pressure_level": 1389,
        "fan_levels": 10000,
        "reheat_regulation_level": 0,
        "cooling_regulation_level": 0,
        "duct_pressure": 0,
        "voc_level": 0,
        "rhx_operation_level": 8400,
        "rhx_efficiency": 0,
        "rhx_defrost_pressure_level": 0,
        "heat_exchanger_regulator_lvl": 0,
        "room_temp_set_point": 16,
        "min_temperature_set_point": 0,
        "max_temperature_set_point": 0
    },
    {
        "timestamp": "2025-03-26T03:00:02.132296",
        "arduino_error": "Error fetching Arduino data: HTTPConnectionPool(host='10.205.104.247', port=80): Max retries exceeded with url: / (Caused by NewConnectionError('<urllib3.connection.HTTPConnection object at 0x7fff7f5aa6d0>: Failed to establish a new connection: [Errno 113] No route to host'))",
        "co2_sensor_data": 0,
        "outdoor_temperature": 6022,
        "supply_air_flow_pressure": 0,
        "supply_air_flow": 13,
        "ahu_filter_pressure_level": 2456,
        "fan_levels": 9343,
        "reheat_regulation_level": 0,
        "cooling_regulation_level": 0,
        "duct_pressure": 0,
        "voc_level": 0,
        "rhx_operation_level": 8402,
        "rhx_efficiency": 0,
        "rhx_defrost_pressure_level": 0,
        "heat_exchanger_regulator_lvl": 0,
        "room_temp_set_point": 16,
        "min_temperature_set_point": 0,
        "max_temperature_set_point": 0
    },
    {
        "timestamp": "2025-03-26T03:10:01.312276",
        "arduino_error": "Error fetching Arduino data: HTTPConnectionPool(host='10.205.104.247', port=80): Max retries exceeded with url: / (Caused by NewConnectionError('<urllib3.connection.HTTPConnection object at 0x7fffa164a6d0>: Failed to establish a new connection: [Errno 113] No route to host'))",
        "co2_sensor_data": 0,
        "outdoor_temperature": 6022,
        "supply_air_flow_pressure": 0,
        "supply_air_flow": 13,
        "ahu_filter_pressure_level": 3569,
        "fan_levels": 10000,
        "reheat_regulation_level": 0,
        "cooling_regulation_level": 0,
        "duct_pressure": 0,
        "voc_level": 0,
        "rhx_operation_level": 8401,
        "rhx_efficiency": 0,
        "rhx_defrost_pressure_level": 0,
        "heat_exchanger_regulator_lvl": 0,
        "room_temp_set_point": 16,
        "min_temperature_set_point": 0,
        "max_temperature_set_point": 0
    },
    {
        "timestamp": "2025-03-26T03:20:01.391736",
        "arduino_error": "Error fetching Arduino data: HTTPConnectionPool(host='10.205.104.247', port=80): Max retries exceeded with url: / (Caused by NewConnectionError('<urllib3.connection.HTTPConnection object at 0x7ffed389a6d0>: Failed to establish a new connection: [Errno 113] No route to host'))",
        "co2_sensor_data": 0,
        "outdoor_temperature": 6022,
        "supply_air_flow_pressure": 0,
        "supply_air_flow": 13,
        "ahu_filter_pressure_level": 2471,
        "fan_levels": 10000,
        "reheat_regulation_level": 0,
        "cooling_regulation_level": 0,
        "duct_pressure": 0,
        "voc_level": 0,
        "rhx_operation_level": 8402,
        "rhx_efficiency": 0,
        "rhx_defrost_pressure_level": 0,
        "heat_exchanger_regulator_lvl": 0,
        "room_temp_set_point": 16,
        "min_temperature_set_point": 0,
        "max_temperature_set_point": 0
    },
    {
        "timestamp": "2025-03-26T03:30:01.597831",
        "arduino_error": "Error fetching Arduino data: HTTPConnectionPool(host='10.205.104.247', port=80): Max retries exceeded with url: / (Caused by NewConnectionError('<urllib3.connection.HTTPConnection object at 0x7fff0c60a6d0>: Failed to establish a new connection: [Errno 113] No route to host'))",
        "co2_sensor_data": 0,
        "outdoor_temperature": 6022,
        "supply_air_flow_pressure": 0,
        "supply_air_flow": 13,
        "ahu_filter_pressure_level": 1870,
        "fan_levels": 10000,
        "reheat_regulation_level": 0,
        "cooling_regulation_level": 0,
        "duct_pressure": 0,
        "voc_level": 0,
        "rhx_operation_level": 8399,
        "rhx_efficiency": 0,
        "rhx_defrost_pressure_level": 0,
        "heat_exchanger_regulator_lvl": 0,
        "room_temp_set_point": 16,
        "min_temperature_set_point": 0,
        "max_temperature_set_point": 0
    },
    {
        "timestamp": "2025-03-26T03:40:01.765545",
        "arduino_error": "Error fetching Arduino data: HTTPConnectionPool(host='10.205.104.247', port=80): Max retries exceeded with url: / (Caused by NewConnectionError('<urllib3.connection.HTTPConnection object at 0x7fff4f40a7d0>: Failed to establish a new connection: [Errno 113] No route to host'))",
        "co2_sensor_data": 0,
        "outdoor_temperature": 6022,
        "supply_air_flow_pressure": 0,
        "supply_air_flow": 13,
        "ahu_filter_pressure_level": 2319,
        "fan_levels": 10000,
        "reheat_regulation_level": 0,
        "cooling_regulation_level": 0,
        "duct_pressure": 0,
        "voc_level": 0,
        "rhx_operation_level": 8398,
        "rhx_efficiency": 0,
        "rhx_defrost_pressure_level": 0,
        "heat_exchanger_regulator_lvl": 0,
        "room_temp_set_point": 16,
        "min_temperature_set_point": 0,
        "max_temperature_set_point": 0
    },
    {
        "timestamp": "2025-03-26T03:50:01.447701",
        "arduino_error": "Error fetching Arduino data: HTTPConnectionPool(host='10.205.104.247', port=80): Max retries exceeded with url: / (Caused by NewConnectionError('<urllib3.connection.HTTPConnection object at 0x7fffa0d5a6d0>: Failed to establish a new connection: [Errno 113] No route to host'))",
        "co2_sensor_data": 0,
        "outdoor_temperature": 6022,
        "supply_air_flow_pressure": 0,
        "supply_air_flow": 13,
        "ahu_filter_pressure_level": 3522,
        "fan_levels": 6834,
        "reheat_regulation_level": 0,
        "cooling_regulation_level": 0,
        "duct_pressure": 0,
        "voc_level": 0,
        "rhx_operation_level": 8400,
        "rhx_efficiency": 0,
        "rhx_defrost_pressure_level": 0,
        "heat_exchanger_regulator_lvl": 0,
        "room_temp_set_point": 16,
        "min_temperature_set_point": 0,
        "max_temperature_set_point": 0
    },
    {
        "timestamp": "2025-03-26T04:00:02.102084",
        "arduino_error": "Error fetching Arduino data: HTTPConnectionPool(host='10.205.104.247', port=80): Max retries exceeded with url: / (Caused by NewConnectionError('<urllib3.connection.HTTPConnection object at 0x7fff6e98a7d0>: Failed to establish a new connection: [Errno 113] No route to host'))",
        "co2_sensor_data": 0,
        "outdoor_temperature": 6022,
        "supply_air_flow_pressure": 0,
        "supply_air_flow": 13,
        "ahu_filter_pressure_level": 3036,
        "fan_levels": 10000,
        "reheat_regulation_level": 0,
        "cooling_regulation_level": 0,
        "duct_pressure": 0,
        "voc_level": 0,
        "rhx_operation_level": 8386,
        "rhx_efficiency": 0,
        "rhx_defrost_pressure_level": 0,
        "heat_exchanger_regulator_lvl": 0,
        "room_temp_set_point": 16,
        "min_temperature_set_point": 0,
        "max_temperature_set_point": 0
    },
    {
        "timestamp": "2025-03-26T04:10:02.110274",
        "arduino_error": "Error fetching Arduino data: HTTPConnectionPool(host='10.205.104.247', port=80): Max retries exceeded with url: / (Caused by NewConnectionError('<urllib3.connection.HTTPConnection object at 0x7ffebf28a6d0>: Failed to establish a new connection: [Errno 113] No route to host'))",
        "co2_sensor_data": 0,
        "outdoor_temperature": 6022,
        "supply_air_flow_pressure": 0,
        "supply_air_flow": 12,
        "ahu_filter_pressure_level": 2011,
        "fan_levels": 10000,
        "reheat_regulation_level": 0,
        "cooling_regulation_level": 0,
        "duct_pressure": 0,
        "voc_level": 0,
        "rhx_operation_level": 8400,
        "rhx_efficiency": 0,
        "rhx_defrost_pressure_level": 0,
        "heat_exchanger_regulator_lvl": 0,
        "room_temp_set_point": 16,
        "min_temperature_set_point": 0,
        "max_temperature_set_point": 0
    },
    {
        "timestamp": "2025-03-26T04:20:01.863390",
        "arduino_error": "Error fetching Arduino data: HTTPConnectionPool(host='10.205.104.247', port=80): Max retries exceeded with url: / (Caused by NewConnectionError('<urllib3.connection.HTTPConnection object at 0x7fff9523a6d0>: Failed to establish a new connection: [Errno 113] No route to host'))",
        "co2_sensor_data": 0,
        "outdoor_temperature": 6022,
        "supply_air_flow_pressure": 0,
        "supply_air_flow": 13,
        "ahu_filter_pressure_level": 1980,
        "fan_levels": 10000,
        "reheat_regulation_level": 0,
        "cooling_regulation_level": 0,
        "duct_pressure": 0,
        "voc_level": 0,
        "rhx_operation_level": 8398,
        "rhx_efficiency": 0,
        "rhx_defrost_pressure_level": 0,
        "heat_exchanger_regulator_lvl": 0,
        "room_temp_set_point": 16,
        "min_temperature_set_point": 0,
        "max_temperature_set_point": 0
    },
    {
        "timestamp": "2025-03-26T04:30:01.562329",
        "arduino_error": "Error fetching Arduino data: HTTPConnectionPool(host='10.205.104.247', port=80): Max retries exceeded with url: / (Caused by NewConnectionError('<urllib3.connection.HTTPConnection object at 0x7fff148aa6d0>: Failed to establish a new connection: [Errno 113] No route to host'))",
        "co2_sensor_data": 0,
        "outdoor_temperature": 6023,
        "supply_air_flow_pressure": 0,
        "supply_air_flow": 13,
        "ahu_filter_pressure_level": 3539,
        "fan_levels": 6380,
        "reheat_regulation_level": 0,
        "cooling_regulation_level": 0,
        "duct_pressure": 0,
        "voc_level": 0,
        "rhx_operation_level": 8328,
        "rhx_efficiency": 0,
        "rhx_defrost_pressure_level": 0,
        "heat_exchanger_regulator_lvl": 0,
        "room_temp_set_point": 16,
        "min_temperature_set_point": 0,
        "max_temperature_set_point": 0
    },
    {
        "timestamp": "2025-03-26T04:40:01.222484",
        "arduino_error": "Error fetching Arduino data: HTTPConnectionPool(host='10.205.104.247', port=80): Max retries exceeded with url: / (Caused by NewConnectionError('<urllib3.connection.HTTPConnection object at 0x7fff5977a6d0>: Failed to establish a new connection: [Errno 113] No route to host'))",
        "co2_sensor_data": 0,
        "outdoor_temperature": 6023,
        "supply_air_flow_pressure": 0,
        "supply_air_flow": 13,
        "ahu_filter_pressure_level": 3101,
        "fan_levels": 10000,
        "reheat_regulation_level": 0,
        "cooling_regulation_level": 0,
        "duct_pressure": 0,
        "voc_level": 0,
        "rhx_operation_level": 8401,
        "rhx_efficiency": 0,
        "rhx_defrost_pressure_level": 0,
        "heat_exchanger_regulator_lvl": 0,
        "room_temp_set_point": 16,
        "min_temperature_set_point": 0,
        "max_temperature_set_point": 0
    },
    {
        "timestamp": "2025-03-26T04:50:01.878606",
        "arduino_error": "Error fetching Arduino data: HTTPConnectionPool(host='10.205.104.247', port=80): Max retries exceeded with url: / (Caused by NewConnectionError('<urllib3.connection.HTTPConnection object at 0x7fff1aa3a6d0>: Failed to establish a new connection: [Errno 113] No route to host'))",
        "co2_sensor_data": 0,
        "outdoor_temperature": 6023,
        "supply_air_flow_pressure": 0,
        "supply_air_flow": 13,
        "ahu_filter_pressure_level": 2121,
        "fan_levels": 10000,
        "reheat_regulation_level": 0,
        "cooling_regulation_level": 0,
        "duct_pressure": 0,
        "voc_level": 0,
        "rhx_operation_level": 8400,
        "rhx_efficiency": 0,
        "rhx_defrost_pressure_level": 0,
        "heat_exchanger_regulator_lvl": 0,
        "room_temp_set_point": 16,
        "min_temperature_set_point": 0,
        "max_temperature_set_point": 0
    },
    {
        "timestamp": "2025-03-26T05:00:01.988651",
        "arduino_error": "Error fetching Arduino data: HTTPConnectionPool(host='10.205.104.247', port=80): Max retries exceeded with url: / (Caused by NewConnectionError('<urllib3.connection.HTTPConnection object at 0x7fff817ca6d0>: Failed to establish a new connection: [Errno 113] No route to host'))",
        "co2_sensor_data": 0,
        "outdoor_temperature": 6023,
        "supply_air_flow_pressure": 0,
        "supply_air_flow": 14,
        "ahu_filter_pressure_level": 2187,
        "fan_levels": 10000,
        "reheat_regulation_level": 0,
        "cooling_regulation_level": 0,
        "duct_pressure": 0,
        "voc_level": 0,
        "rhx_operation_level": 8400,
        "rhx_efficiency": 0,
        "rhx_defrost_pressure_level": 0,
        "heat_exchanger_regulator_lvl": 0,
        "room_temp_set_point": 16,
        "min_temperature_set_point": 0,
        "max_temperature_set_point": 0
    },
    {
        "timestamp": "2025-03-26T05:10:01.705816",
        "arduino_error": "Error fetching Arduino data: HTTPConnectionPool(host='10.205.104.247', port=80): Max retries exceeded with url: / (Caused by NewConnectionError('<urllib3.connection.HTTPConnection object at 0x7fffa01fa7d0>: Failed to establish a new connection: [Errno 113] No route to host'))",
        "co2_sensor_data": 0,
        "outdoor_temperature": 6023,
        "supply_air_flow_pressure": 0,
        "supply_air_flow": 13,
        "ahu_filter_pressure_level": 2578,
        "fan_levels": 9825,
        "reheat_regulation_level": 0,
        "cooling_regulation_level": 0,
        "duct_pressure": 0,
        "voc_level": 0,
        "rhx_operation_level": 8401,
        "rhx_efficiency": 0,
        "rhx_defrost_pressure_level": 0,
        "heat_exchanger_regulator_lvl": 0,
        "room_temp_set_point": 16,
        "min_temperature_set_point": 0,
        "max_temperature_set_point": 0
    },
    {
        "timestamp": "2025-03-26T05:20:01.430906",
        "arduino_error": "Error fetching Arduino data: HTTPConnectionPool(host='10.205.104.247', port=80): Max retries exceeded with url: / (Caused by NewConnectionError('<urllib3.connection.HTTPConnection object at 0x7fff4b4aa7d0>: Failed to establish a new connection: [Errno 113] No route to host'))",
        "co2_sensor_data": 0,
        "outdoor_temperature": 6023,
        "supply_air_flow_pressure": 0,
        "supply_air_flow": 12,
        "ahu_filter_pressure_level": 3630,
        "fan_levels": 10000,
        "reheat_regulation_level": 0,
        "cooling_regulation_level": 0,
        "duct_pressure": 0,
        "voc_level": 0,
        "rhx_operation_level": 8397,
        "rhx_efficiency": 0,
        "rhx_defrost_pressure_level": 0,
        "heat_exchanger_regulator_lvl": 0,
        "room_temp_set_point": 16,
        "min_temperature_set_point": 0,
        "max_temperature_set_point": 0
    },
    {
        "timestamp": "2025-03-26T05:30:02.101480",
        "arduino_error": "Error fetching Arduino data: HTTPConnectionPool(host='10.205.104.247', port=80): Max retries exceeded with url: / (Caused by NewConnectionError('<urllib3.connection.HTTPConnection object at 0x7fff1b8ea6d0>: Failed to establish a new connection: [Errno 113] No route to host'))",
        "co2_sensor_data": 0,
        "outdoor_temperature": 6023,
        "supply_air_flow_pressure": 0,
        "supply_air_flow": 12,
        "ahu_filter_pressure_level": 2540,
        "fan_levels": 10000,
        "reheat_regulation_level": 0,
        "cooling_regulation_level": 0,
        "duct_pressure": 0,
        "voc_level": 0,
        "rhx_operation_level": 8401,
        "rhx_efficiency": 0,
        "rhx_defrost_pressure_level": 0,
        "heat_exchanger_regulator_lvl": 0,
        "room_temp_set_point": 16,
        "min_temperature_set_point": 0,
        "max_temperature_set_point": 0
    },
    {
        "timestamp": "2025-03-26T05:40:01.830647",
        "arduino_error": "Error fetching Arduino data: HTTPConnectionPool(host='10.205.104.247', port=80): Max retries exceeded with url: / (Caused by NewConnectionError('<urllib3.connection.HTTPConnection object at 0x7fff538aa6d0>: Failed to establish a new connection: [Errno 113] No route to host'))",
        "co2_sensor_data": 0,
        "outdoor_temperature": 6023,
        "supply_air_flow_pressure": 0,
        "supply_air_flow": 13,
        "ahu_filter_pressure_level": 2143,
        "fan_levels": 10000,
        "reheat_regulation_level": 0,
        "cooling_regulation_level": 0,
        "duct_pressure": 0,
        "voc_level": 0,
        "rhx_operation_level": 8399,
        "rhx_efficiency": 0,
        "rhx_defrost_pressure_level": 0,
        "heat_exchanger_regulator_lvl": 0,
        "room_temp_set_point": 16,
        "min_temperature_set_point": 0,
        "max_temperature_set_point": 0
    },
    {
        "timestamp": "2025-03-26T05:50:01.623581",
        "arduino_error": "Error fetching Arduino data: HTTPConnectionPool(host='10.205.104.247', port=80): Max retries exceeded with url: / (Caused by NewConnectionError('<urllib3.connection.HTTPConnection object at 0x7ffed1b2a7d0>: Failed to establish a new connection: [Errno 113] No route to host'))",
        "co2_sensor_data": 0,
        "outdoor_temperature": 6023,
        "supply_air_flow_pressure": 0,
        "supply_air_flow": 13,
        "ahu_filter_pressure_level": 2581,
        "fan_levels": 9889,
        "reheat_regulation_level": 0,
        "cooling_regulation_level": 0,
        "duct_pressure": 0,
        "voc_level": 0,
        "rhx_operation_level": 8402,
        "rhx_efficiency": 0,
        "rhx_defrost_pressure_level": 0,
        "heat_exchanger_regulator_lvl": 0,
        "room_temp_set_point": 16,
        "min_temperature_set_point": 0,
        "max_temperature_set_point": 0
    },
    {
        "timestamp": "2025-03-26T06:00:01.282668",
        "arduino_error": "Error fetching Arduino data: HTTPConnectionPool(host='10.205.104.247', port=80): Max retries exceeded with url: / (Caused by NewConnectionError('<urllib3.connection.HTTPConnection object at 0x7ffec96ca6d0>: Failed to establish a new connection: [Errno 113] No route to host'))",
        "co2_sensor_data": 0,
        "outdoor_temperature": 6023,
        "supply_air_flow_pressure": 0,
        "supply_air_flow": 13,
        "ahu_filter_pressure_level": 3637,
        "fan_levels": 10000,
        "reheat_regulation_level": 0,
        "cooling_regulation_level": 0,
        "duct_pressure": 0,
        "voc_level": 0,
        "rhx_operation_level": 8400,
        "rhx_efficiency": 0,
        "rhx_defrost_pressure_level": 0,
        "heat_exchanger_regulator_lvl": 0,
        "room_temp_set_point": 16,
        "min_temperature_set_point": 0,
        "max_temperature_set_point": 0
    },
    {
        "timestamp": "2025-03-26T06:10:01.963594",
        "arduino_error": "Error fetching Arduino data: HTTPConnectionPool(host='10.205.104.247', port=80): Max retries exceeded with url: / (Caused by NewConnectionError('<urllib3.connection.HTTPConnection object at 0x7fff5e8aa6d0>: Failed to establish a new connection: [Errno 113] No route to host'))",
        "co2_sensor_data": 0,
        "outdoor_temperature": 6023,
        "supply_air_flow_pressure": 0,
        "supply_air_flow": 12,
        "ahu_filter_pressure_level": 2769,
        "fan_levels": 10000,
        "reheat_regulation_level": 0,
        "cooling_regulation_level": 0,
        "duct_pressure": 0,
        "voc_level": 0,
        "rhx_operation_level": 8400,
        "rhx_efficiency": 0,
        "rhx_defrost_pressure_level": 0,
        "heat_exchanger_regulator_lvl": 0,
        "room_temp_set_point": 16,
        "min_temperature_set_point": 0,
        "max_temperature_set_point": 0
    },
    {
        "timestamp": "2025-03-26T06:20:01.577905",
        "arduino_error": "Error fetching Arduino data: HTTPConnectionPool(host='10.205.104.247', port=80): Max retries exceeded with url: / (Caused by NewConnectionError('<urllib3.connection.HTTPConnection object at 0x7fff81e7a6d0>: Failed to establish a new connection: [Errno 113] No route to host'))",
        "co2_sensor_data": 0,
        "outdoor_temperature": 6023,
        "supply_air_flow_pressure": 0,
        "supply_air_flow": 13,
        "ahu_filter_pressure_level": 2116,
        "fan_levels": 10000,
        "reheat_regulation_level": 0,
        "cooling_regulation_level": 0,
        "duct_pressure": 0,
        "voc_level": 0,
        "rhx_operation_level": 8400,
        "rhx_efficiency": 0,
        "rhx_defrost_pressure_level": 0,
        "heat_exchanger_regulator_lvl": 0,
        "room_temp_set_point": 16,
        "min_temperature_set_point": 0,
        "max_temperature_set_point": 0
    },
    {
        "timestamp": "2025-03-26T06:30:01.266853",
        "arduino_error": "Error fetching Arduino data: HTTPConnectionPool(host='10.205.104.247', port=80): Max retries exceeded with url: / (Caused by NewConnectionError('<urllib3.connection.HTTPConnection object at 0x7fff9379a6d0>: Failed to establish a new connection: [Errno 113] No route to host'))",
        "co2_sensor_data": 0,
        "outdoor_temperature": 6023,
        "supply_air_flow_pressure": 0,
        "supply_air_flow": 13,
        "ahu_filter_pressure_level": 2464,
        "fan_levels": 10000,
        "reheat_regulation_level": 0,
        "cooling_regulation_level": 0,
        "duct_pressure": 0,
        "voc_level": 0,
        "rhx_operation_level": 8400,
        "rhx_efficiency": 0,
        "rhx_defrost_pressure_level": 0,
        "heat_exchanger_regulator_lvl": 0,
        "room_temp_set_point": 16,
        "min_temperature_set_point": 0,
        "max_temperature_set_point": 0
    },
    {
        "timestamp": "2025-03-26T06:40:01.943690",
        "arduino_error": "Error fetching Arduino data: HTTPConnectionPool(host='10.205.104.247', port=80): Max retries exceeded with url: / (Caused by NewConnectionError('<urllib3.connection.HTTPConnection object at 0x7fff82eea7d0>: Failed to establish a new connection: [Errno 113] No route to host'))",
        "co2_sensor_data": 0,
        "outdoor_temperature": 6023,
        "supply_air_flow_pressure": 0,
        "supply_air_flow": 35,
        "ahu_filter_pressure_level": 3694,
        "fan_levels": 6739,
        "reheat_regulation_level": 0,
        "cooling_regulation_level": 0,
        "duct_pressure": 0,
        "voc_level": 0,
        "rhx_operation_level": 8323,
        "rhx_efficiency": 0,
        "rhx_defrost_pressure_level": 0,
        "heat_exchanger_regulator_lvl": 0,
        "room_temp_set_point": 16,
        "min_temperature_set_point": 0,
        "max_temperature_set_point": 0
    },
    {
        "timestamp": "2025-03-26T06:50:01.600603",
        "arduino_error": "Error fetching Arduino data: HTTPConnectionPool(host='10.205.104.247', port=80): Max retries exceeded with url: / (Caused by NewConnectionError('<urllib3.connection.HTTPConnection object at 0x7fff4e6da6d0>: Failed to establish a new connection: [Errno 113] No route to host'))",
        "co2_sensor_data": 0,
        "outdoor_temperature": 6023,
        "supply_air_flow_pressure": 0,
        "supply_air_flow": 35,
        "ahu_filter_pressure_level": 2737,
        "fan_levels": 10000,
        "reheat_regulation_level": 0,
        "cooling_regulation_level": 0,
        "duct_pressure": 0,
        "voc_level": 0,
        "rhx_operation_level": 8304,
        "rhx_efficiency": 0,
        "rhx_defrost_pressure_level": 0,
        "heat_exchanger_regulator_lvl": 0,
        "room_temp_set_point": 16,
        "min_temperature_set_point": 0,
        "max_temperature_set_point": 0
    },
    {
        "timestamp": "2025-03-26T07:00:01.222147",
        "arduino_error": "Error fetching Arduino data: HTTPConnectionPool(host='10.205.104.247', port=80): Max retries exceeded with url: / (Caused by NewConnectionError('<urllib3.connection.HTTPConnection object at 0x7ffec444a7d0>: Failed to establish a new connection: [Errno 113] No route to host'))",
        "co2_sensor_data": 0,
        "outdoor_temperature": 6023,
        "supply_air_flow_pressure": 0,
        "supply_air_flow": 34,
        "ahu_filter_pressure_level": 1738,
        "fan_levels": 10000,
        "reheat_regulation_level": 0,
        "cooling_regulation_level": 0,
        "duct_pressure": 0,
        "voc_level": 0,
        "rhx_operation_level": 8300,
        "rhx_efficiency": 0,
        "rhx_defrost_pressure_level": 0,
        "heat_exchanger_regulator_lvl": 0,
        "room_temp_set_point": 16,
        "min_temperature_set_point": 0,
        "max_temperature_set_point": 0
    },
    {
        "timestamp": "2025-03-26T07:10:01.854725",
        "arduino_error": "Error fetching Arduino data: HTTPConnectionPool(host='10.205.104.247', port=80): Max retries exceeded with url: / (Caused by NewConnectionError('<urllib3.connection.HTTPConnection object at 0x7fffb15fa6d0>: Failed to establish a new connection: [Errno 113] No route to host'))",
        "co2_sensor_data": 0,
        "outdoor_temperature": 6023,
        "supply_air_flow_pressure": 0,
        "supply_air_flow": 34,
        "ahu_filter_pressure_level": 1771,
        "fan_levels": 10000,
        "reheat_regulation_level": 0,
        "cooling_regulation_level": 0,
        "duct_pressure": 0,
        "voc_level": 0,
        "rhx_operation_level": 8300,
        "rhx_efficiency": 0,
        "rhx_defrost_pressure_level": 0,
        "heat_exchanger_regulator_lvl": 0,
        "room_temp_set_point": 16,
        "min_temperature_set_point": 0,
        "max_temperature_set_point": 0
    },
    {
        "timestamp": "2025-03-26T07:20:01.556239",
        "arduino_error": "Error fetching Arduino data: HTTPConnectionPool(host='10.205.104.247', port=80): Max retries exceeded with url: / (Caused by NewConnectionError('<urllib3.connection.HTTPConnection object at 0x7fff94a2a7d0>: Failed to establish a new connection: [Errno 113] No route to host'))",
        "co2_sensor_data": 0,
        "outdoor_temperature": 6023,
        "supply_air_flow_pressure": 0,
        "supply_air_flow": 35,
        "ahu_filter_pressure_level": 2892,
        "fan_levels": 7966,
        "reheat_regulation_level": 0,
        "cooling_regulation_level": 0,
        "duct_pressure": 0,
        "voc_level": 0,
        "rhx_operation_level": 8306,
        "rhx_efficiency": 0,
        "rhx_defrost_pressure_level": 0,
        "heat_exchanger_regulator_lvl": 0,
        "room_temp_set_point": 16,
        "min_temperature_set_point": 0,
        "max_temperature_set_point": 0
    },
    {
        "timestamp": "2025-03-26T07:30:01.275185",
        "arduino_error": "Error fetching Arduino data: HTTPConnectionPool(host='10.205.104.247', port=80): Max retries exceeded with url: / (Caused by NewConnectionError('<urllib3.connection.HTTPConnection object at 0x7ffef80fa7d0>: Failed to establish a new connection: [Errno 113] No route to host'))",
        "co2_sensor_data": 0,
        "outdoor_temperature": 6023,
        "supply_air_flow_pressure": 0,
        "supply_air_flow": 35,
        "ahu_filter_pressure_level": 3175,
        "fan_levels": 10000,
        "reheat_regulation_level": 0,
        "cooling_regulation_level": 0,
        "duct_pressure": 0,
        "voc_level": 0,
        "rhx_operation_level": 8301,
        "rhx_efficiency": 0,
        "rhx_defrost_pressure_level": 0,
        "heat_exchanger_regulator_lvl": 0,
        "room_temp_set_point": 16,
        "min_temperature_set_point": 0,
        "max_temperature_set_point": 0
    },
    {
        "timestamp": "2025-03-26T07:40:02.033477",
        "arduino_error": "Error fetching Arduino data: HTTPConnectionPool(host='10.205.104.247', port=80): Max retries exceeded with url: / (Caused by NewConnectionError('<urllib3.connection.HTTPConnection object at 0x7fff5367a6d0>: Failed to establish a new connection: [Errno 113] No route to host'))",
        "co2_sensor_data": 0,
        "outdoor_temperature": 6023,
        "supply_air_flow_pressure": 0,
        "supply_air_flow": 35,
        "ahu_filter_pressure_level": 2119,
        "fan_levels": 10000,
        "reheat_regulation_level": 0,
        "cooling_regulation_level": 0,
        "duct_pressure": 0,
        "voc_level": 0,
        "rhx_operation_level": 8300,
        "rhx_efficiency": 0,
        "rhx_defrost_pressure_level": 0,
        "heat_exchanger_regulator_lvl": 0,
        "room_temp_set_point": 16,
        "min_temperature_set_point": 0,
        "max_temperature_set_point": 0
    },
    {
        "timestamp": "2025-03-26T07:50:01.720062",
        "arduino_error": "Error fetching Arduino data: HTTPConnectionPool(host='10.205.104.247', port=80): Max retries exceeded with url: / (Caused by NewConnectionError('<urllib3.connection.HTTPConnection object at 0x7ffefa2ba6d0>: Failed to establish a new connection: [Errno 113] No route to host'))",
        "co2_sensor_data": 0,
        "outdoor_temperature": 6023,
        "supply_air_flow_pressure": 0,
        "supply_air_flow": 34,
        "ahu_filter_pressure_level": 1705,
        "fan_levels": 4089,
        "reheat_regulation_level": 0,
        "cooling_regulation_level": 0,
        "duct_pressure": 0,
        "voc_level": 0,
        "rhx_operation_level": 8300,
        "rhx_efficiency": 0,
        "rhx_defrost_pressure_level": 0,
        "heat_exchanger_regulator_lvl": 0,
        "room_temp_set_point": 16,
        "min_temperature_set_point": 0,
        "max_temperature_set_point": 0
    },
    {
        "timestamp": "2025-03-26T08:00:01.453916",
        "arduino_error": "Error fetching Arduino data: HTTPConnectionPool(host='10.205.104.247', port=80): Max retries exceeded with url: / (Caused by NewConnectionError('<urllib3.connection.HTTPConnection object at 0x7fff3f31a6d0>: Failed to establish a new connection: [Errno 113] No route to host'))",
        "co2_sensor_data": 0,
        "outdoor_temperature": 6023,
        "supply_air_flow_pressure": 0,
        "supply_air_flow": 34,
        "ahu_filter_pressure_level": 3519,
        "fan_levels": 6620,
        "reheat_regulation_level": 0,
        "cooling_regulation_level": 0,
        "duct_pressure": 0,
        "voc_level": 0,
        "rhx_operation_level": 8300,
        "rhx_efficiency": 0,
        "rhx_defrost_pressure_level": 0,
        "heat_exchanger_regulator_lvl": 0,
        "room_temp_set_point": 16,
        "min_temperature_set_point": 0,
        "max_temperature_set_point": 0
    },
    {
        "timestamp": "2025-03-26T08:10:01.445303",
        "arduino_error": "Error fetching Arduino data: HTTPConnectionPool(host='10.205.104.247', port=80): Max retries exceeded with url: / (Caused by NewConnectionError('<urllib3.connection.HTTPConnection object at 0x7ffeebf5a7d0>: Failed to establish a new connection: [Errno 113] No route to host'))",
        "co2_sensor_data": 0,
        "outdoor_temperature": 6023,
        "supply_air_flow_pressure": 0,
        "supply_air_flow": 33,
        "ahu_filter_pressure_level": 2888,
        "fan_levels": 10000,
        "reheat_regulation_level": 0,
        "cooling_regulation_level": 0,
        "duct_pressure": 0,
        "voc_level": 0,
        "rhx_operation_level": 8301,
        "rhx_efficiency": 0,
        "rhx_defrost_pressure_level": 0,
        "heat_exchanger_regulator_lvl": 0,
        "room_temp_set_point": 16,
        "min_temperature_set_point": 0,
        "max_temperature_set_point": 0
    },
    {
        "timestamp": "2025-03-26T08:20:01.437518",
        "arduino_error": "Error fetching Arduino data: HTTPConnectionPool(host='10.205.104.247', port=80): Max retries exceeded with url: / (Caused by NewConnectionError('<urllib3.connection.HTTPConnection object at 0x7fffb3cea6d0>: Failed to establish a new connection: [Errno 113] No route to host'))",
        "co2_sensor_data": 0,
        "outdoor_temperature": 6023,
        "supply_air_flow_pressure": 0,
        "supply_air_flow": 33,
        "ahu_filter_pressure_level": 1274,
        "fan_levels": 10000,
        "reheat_regulation_level": 0,
        "cooling_regulation_level": 0,
        "duct_pressure": 0,
        "voc_level": 0,
        "rhx_operation_level": 8305,
        "rhx_efficiency": 0,
        "rhx_defrost_pressure_level": 0,
        "heat_exchanger_regulator_lvl": 0,
        "room_temp_set_point": 16,
        "min_temperature_set_point": 0,
        "max_temperature_set_point": 0
    },
    {
        "timestamp": "2025-03-26T08:30:01.488020",
        "arduino_error": "Error fetching Arduino data: HTTPConnectionPool(host='10.205.104.247', port=80): Max retries exceeded with url: / (Caused by NewConnectionError('<urllib3.connection.HTTPConnection object at 0x7fffb03aa7d0>: Failed to establish a new connection: [Errno 113] No route to host'))",
        "co2_sensor_data": 0,
        "outdoor_temperature": 6023,
        "supply_air_flow_pressure": 0,
        "supply_air_flow": 34,
        "ahu_filter_pressure_level": 2108,
        "fan_levels": 7327,
        "reheat_regulation_level": 0,
        "cooling_regulation_level": 0,
        "duct_pressure": 0,
        "voc_level": 0,
        "rhx_operation_level": 8300,
        "rhx_efficiency": 0,
        "rhx_defrost_pressure_level": 0,
        "heat_exchanger_regulator_lvl": 0,
        "room_temp_set_point": 16,
        "min_temperature_set_point": 0,
        "max_temperature_set_point": 0
    },
    {
        "timestamp": "2025-03-26T08:40:02.123242",
        "arduino_error": "Error fetching Arduino data: HTTPConnectionPool(host='10.205.104.247', port=80): Max retries exceeded with url: / (Caused by NewConnectionError('<urllib3.connection.HTTPConnection object at 0x7fff277ba7d0>: Failed to establish a new connection: [Errno 113] No route to host'))",
        "co2_sensor_data": 0,
        "outdoor_temperature": 6023,
        "supply_air_flow_pressure": 0,
        "supply_air_flow": 34,
        "ahu_filter_pressure_level": 3053,
        "fan_levels": 5528,
        "reheat_regulation_level": 0,
        "cooling_regulation_level": 0,
        "duct_pressure": 0,
        "voc_level": 0,
        "rhx_operation_level": 8301,
        "rhx_efficiency": 0,
        "rhx_defrost_pressure_level": 0,
        "heat_exchanger_regulator_lvl": 0,
        "room_temp_set_point": 16,
        "min_temperature_set_point": 0,
        "max_temperature_set_point": 0
    },
    {
        "timestamp": "2025-03-26T08:50:02.124331",
        "arduino_error": "Error fetching Arduino data: HTTPConnectionPool(host='10.205.104.247', port=80): Max retries exceeded with url: / (Caused by NewConnectionError('<urllib3.connection.HTTPConnection object at 0x7fff0288a6d0>: Failed to establish a new connection: [Errno 113] No route to host'))",
        "co2_sensor_data": 0,
        "outdoor_temperature": 6023,
        "supply_air_flow_pressure": 0,
        "supply_air_flow": 33,
        "ahu_filter_pressure_level": 3160,
        "fan_levels": 10000,
        "reheat_regulation_level": 0,
        "cooling_regulation_level": 0,
        "duct_pressure": 0,
        "voc_level": 0,
        "rhx_operation_level": 8305,
        "rhx_efficiency": 0,
        "rhx_defrost_pressure_level": 0,
        "heat_exchanger_regulator_lvl": 0,
        "room_temp_set_point": 16,
        "min_temperature_set_point": 0,
        "max_temperature_set_point": 0
    },
    {
        "timestamp": "2025-03-26T09:00:01.604370",
        "arduino_error": "Error fetching Arduino data: HTTPConnectionPool(host='10.205.104.247', port=80): Max retries exceeded with url: / (Caused by NewConnectionError('<urllib3.connection.HTTPConnection object at 0x7fff218aa6d0>: Failed to establish a new connection: [Errno 113] No route to host'))",
        "co2_sensor_data": 0,
        "outdoor_temperature": 6023,
        "supply_air_flow_pressure": 0,
        "supply_air_flow": 34,
        "ahu_filter_pressure_level": 2417,
        "fan_levels": 10000,
        "reheat_regulation_level": 0,
        "cooling_regulation_level": 0,
        "duct_pressure": 0,
        "voc_level": 0,
        "rhx_operation_level": 8303,
        "rhx_efficiency": 0,
        "rhx_defrost_pressure_level": 0,
        "heat_exchanger_regulator_lvl": 0,
        "room_temp_set_point": 16,
        "min_temperature_set_point": 0,
        "max_temperature_set_point": 0
    },
    {
        "timestamp": "2025-03-26T09:10:01.668036",
        "arduino_error": "Error fetching Arduino data: HTTPConnectionPool(host='10.205.104.247', port=80): Max retries exceeded with url: / (Caused by NewConnectionError('<urllib3.connection.HTTPConnection object at 0x7ffec756a6d0>: Failed to establish a new connection: [Errno 113] No route to host'))",
        "co2_sensor_data": 0,
        "outdoor_temperature": 6023,
        "supply_air_flow_pressure": 0,
        "supply_air_flow": 35,
        "ahu_filter_pressure_level": 1143,
        "fan_levels": 10000,
        "reheat_regulation_level": 0,
        "cooling_regulation_level": 0,
        "duct_pressure": 0,
        "voc_level": 0,
        "rhx_operation_level": 8304,
        "rhx_efficiency": 0,
        "rhx_defrost_pressure_level": 0,
        "heat_exchanger_regulator_lvl": 0,
        "room_temp_set_point": 16,
        "min_temperature_set_point": 0,
        "max_temperature_set_point": 0
    },
    {
        "timestamp": "2025-03-26T09:20:01.814204",
        "arduino_error": "Error fetching Arduino data: HTTPConnectionPool(host='10.205.104.247', port=80): Max retries exceeded with url: / (Caused by NewConnectionError('<urllib3.connection.HTTPConnection object at 0x7fff398ba6d0>: Failed to establish a new connection: [Errno 113] No route to host'))",
        "co2_sensor_data": 0,
        "outdoor_temperature": 6023,
        "supply_air_flow_pressure": 0,
        "supply_air_flow": 35,
        "ahu_filter_pressure_level": 2668,
        "fan_levels": 5343,
        "reheat_regulation_level": 0,
        "cooling_regulation_level": 0,
        "duct_pressure": 0,
        "voc_level": 0,
        "rhx_operation_level": 8304,
        "rhx_efficiency": 0,
        "rhx_defrost_pressure_level": 0,
        "heat_exchanger_regulator_lvl": 0,
        "room_temp_set_point": 16,
        "min_temperature_set_point": 0,
        "max_temperature_set_point": 0
    },
    {
        "timestamp": "2025-03-26T09:30:01.585320",
        "arduino_error": "Error fetching Arduino data: HTTPConnectionPool(host='10.205.104.247', port=80): Max retries exceeded with url: / (Caused by NewConnectionError('<urllib3.connection.HTTPConnection object at 0x7fff1939a6d0>: Failed to establish a new connection: [Errno 113] No route to host'))",
        "co2_sensor_data": 0,
        "outdoor_temperature": 6023,
        "supply_air_flow_pressure": 0,
        "supply_air_flow": 35,
        "ahu_filter_pressure_level": 3664,
        "fan_levels": 7053,
        "reheat_regulation_level": 0,
        "cooling_regulation_level": 0,
        "duct_pressure": 0,
        "voc_level": 0,
        "rhx_operation_level": 8304,
        "rhx_efficiency": 0,
        "rhx_defrost_pressure_level": 0,
        "heat_exchanger_regulator_lvl": 0,
        "room_temp_set_point": 16,
        "min_temperature_set_point": 0,
        "max_temperature_set_point": 0
    },
    {
        "timestamp": "2025-03-26T09:40:01.236869",
        "arduino_error": "Error fetching Arduino data: HTTPConnectionPool(host='10.205.104.247', port=80): Max retries exceeded with url: / (Caused by NewConnectionError('<urllib3.connection.HTTPConnection object at 0x7fff2085a6d0>: Failed to establish a new connection: [Errno 113] No route to host'))",
        "co2_sensor_data": 0,
        "outdoor_temperature": 6023,
        "supply_air_flow_pressure": 0,
        "supply_air_flow": 35,
        "ahu_filter_pressure_level": 2637,
        "fan_levels": 10000,
        "reheat_regulation_level": 0,
        "cooling_regulation_level": 0,
        "duct_pressure": 0,
        "voc_level": 0,
        "rhx_operation_level": 8306,
        "rhx_efficiency": 0,
        "rhx_defrost_pressure_level": 0,
        "heat_exchanger_regulator_lvl": 0,
        "room_temp_set_point": 16,
        "min_temperature_set_point": 0,
        "max_temperature_set_point": 0
    },
    {
        "timestamp": "2025-03-26T09:50:01.605625",
        "arduino_error": "Error fetching Arduino data: HTTPConnectionPool(host='10.205.104.247', port=80): Max retries exceeded with url: / (Caused by NewConnectionError('<urllib3.connection.HTTPConnection object at 0x7ffebdcea7d0>: Failed to establish a new connection: [Errno 113] No route to host'))",
        "co2_sensor_data": 0,
        "outdoor_temperature": 6023,
        "supply_air_flow_pressure": 0,
        "supply_air_flow": 36,
        "ahu_filter_pressure_level": 1269,
        "fan_levels": 10000,
        "reheat_regulation_level": 0,
        "cooling_regulation_level": 0,
        "duct_pressure": 0,
        "voc_level": 0,
        "rhx_operation_level": 8300,
        "rhx_efficiency": 0,
        "rhx_defrost_pressure_level": 0,
        "heat_exchanger_regulator_lvl": 0,
        "room_temp_set_point": 16,
        "min_temperature_set_point": 0,
        "max_temperature_set_point": 0
    },
    {
        "timestamp": "2025-03-26T10:00:01.566336",
        "arduino_error": "Error fetching Arduino data: HTTPConnectionPool(host='10.205.104.247', port=80): Max retries exceeded with url: / (Caused by NewConnectionError('<urllib3.connection.HTTPConnection object at 0x7fff976dddd0>: Failed to establish a new connection: [Errno 113] No route to host'))",
        "co2_sensor_data": 0,
        "outdoor_temperature": 6023,
        "supply_air_flow_pressure": 0,
        "supply_air_flow": 35,
        "ahu_filter_pressure_level": 2082,
        "fan_levels": 5572,
        "reheat_regulation_level": 0,
        "cooling_regulation_level": 0,
        "duct_pressure": 0,
        "voc_level": 0,
        "rhx_operation_level": 8302,
        "rhx_efficiency": 0,
        "rhx_defrost_pressure_level": 0,
        "heat_exchanger_regulator_lvl": 0,
        "room_temp_set_point": 16,
        "min_temperature_set_point": 0,
        "max_temperature_set_point": 0
    }
]